{
  "id": "7e8d94bde58a9f664d45c3dc8105eace",
  "source": "Lankadeepa",
  "headline": "සජිත්ගෙන් බන්දුලට විවාදයකට අභියෝගයක්",
  "content": "ආර්ථිකය ගැන දින හතක විවාදයකට එන්නැයි විපක්ෂ නායක සජිත් ප්‍රේමදාස මහතා ප්‍රවාහන හා මහා මහාමාර්ග අමාත්‍ය බන්දුල ගුණවර්ධන මහතාට පාර්ලිමේන්තුවේ දී අභියෝගයක් කළේ ය.\n\nසිංහල සහ ඉංග්‍රීසි භාෂාවෙන් පමණක් නොව දෙමළ භාෂාවෙන් ද ඒ විවාදයට තමා සූදානම් යැයි විපක්ෂ නායක වරයා කීය.\n\nමෙහිදී අමාත්‍ය බන්දුල ගුණවර්ධන මහතා කීවේ තම මව දස මසක් කුසේ තබාගෙන කිරි දුන් සිංහල භාෂාවෙන් දින හතක් නොව පැය තුනක්  විවාදයට ප්‍රමාණවත්  බවයි. රාජ්‍ය මූල්‍ය සම්බන්ධයෙන් විපක්ෂ නායකවරයා සමග අදාල විවාදයට සූදානම් බවද අමාත්‍ය බන්දුල ගුණවර්ධන මහතා කීය.",
  "timestamp": "2023-11-24T00:00:00",
  "url": "https://www.lankadeepa.lk/news/සජතගන-බනදලට-වවදයකට-අභයගයක/101-643480"
}