{
  "id": "be2aced07b4184cd7cd8e7c1b83d36e5",
  "source": "Lankadeepa",
  "headline": "ලෝකයේ නැව් හැදුවේ නැංගුරම්ලා තියන්න නෙවෙයි",
  "content": "ලෝකයේ නැව් නිර්මාණය කළේ නිකන් ඔහේ  නැංගුරම්ලා තැබීමට නොවේ යැයි  ශ්‍රී ලංකා පොදු ජනපෙරමුණේ ජනාධිපති අපේක්ෂක පාර්ලිමේන්තු මන්ත්‍රී නීතිඥ නාමල් රාජපක්ෂ මහතා පැවසීය.\n\nඔහු මෙසේ පැවසුවේ සිය ෆේස්බුක් ගිණුමේ සටහනක් තබමිනි.\n\nතමා අභියෝගය බාරගෙන ජනාධිපති සටනට පිවිසුණු බව සඳහන් කරන  රාජපක්ෂ මහතා නැවක් වරායේ තිබෙන තුරු සුරක්ෂිත බව ද සඳහන් කළේය.\n\nමේ සටන ජයග්‍රහණයෙන් අවසන් කරන බවත් ශ්‍රී ලංකා පොදු ජන පෙරමුණ තමා කෙරෙහි  තබූ  විශ්වාසය ගැන ස්තූතිවන්ත වෙන බවත් ඔහු සඳහන් කළේය.",
  "timestamp": "2024-08-08T00:00:00",
  "url": "https://www.lankadeepa.lk/politics/ලකය-නව-හදව-නගරමල-තයනන-නවය/13-656405"
}