{
  "id": "f55f6395904ce56c570f6b9e34f58d94",
  "source": "hirunews",
  "headline": "\"මැණිකේ\" නිසා යොහානිට ලැබුණු තනතුර ? (වීඩියෝ)",
  "content": "සංගීත ලෝකයේ පෙරලියක් කල ශ්‍රී ලංකාවේ නව පරපුරේ ගායන ශිල්පිනියක් වන යොහානි විසින් ගායනා කරන ලද \"මැණිකේ\" ගීතය පිළිබඳව අලුත්ම කතාබහක් ඇතිව තිබෙනවා.ඒ ශ්‍රී ලංකාවේ ඉන්දීය මහකොමසාරිස්වරයාද අදාල ගීතය පිළිබඳව අදහස් පළකරමින් තානාපති කාර්යාලයේ නිල ට්විටර් ගිණුමේ පණිවුඩයක් තැබීමත් සමඟයි.එහි සඳහන් වන්නේ යොහානි මේ වනවිට දෙරටේ සංස්කෘතික තානාපතිවරිය බවට පත්ව ඇති බවයි.යොහානි පසුගිය දිනක ඉන්දියාවේ ප්‍රමුඛතම රූපවාහිනී නාලිකාවක් වන NDTV නාලිකාවේ වැඩසටහනකට ඔන්ලයින් සම්බන්ධ වෙමින් පැවැත්වූ සම්මුඛ සාකච්ඡාවකට එක්වීම පිළිබඳව සිය ප්‍රසාදය පළකරමින් මෙම සටහන තබා තිබෙනවා.එම ට්විටර් සටහන පහතින්.",
  "timestamp": "2021-09-20T13:35:18",
  "url": "https://hirunews.lk/entertainment/282734/මැණිකේ-නිසා-යොහානිට-ලැබුණු-තනතුර-වීඩියෝ",
  "category": "Entertainment"
}