{
  "id": "b467acf8d12682f4096c138677ee14d2",
  "source": "hirunews",
  "headline": "ටොම් කෲස්ගෙන් Mission: Impossible හරහා ගිනස් ලෝක වාර්තාවක්",
  "content": "ටොම් කෲස් 'Mission: Impossible - The Final Reckoningහි ඊතන් හන්ට් ලෙස ඔහුගේ චරිතය නැවත පන පොවන අතර, එහිදී ඔහු ලෝක වාර්තාවක් පිහිටුවා තිබෙනවා.  බොක්ස් ඔෆිස් වාර්තා කිහිපයක් බිඳ දැමීමෙන් පසුවයි ඔහු මෙලෙස ගිනස් ලෝක වාර්තාව දිනා ඇත්තේ.  ගිනස් ලෝක වාර්තා පොතට අනුව, කෲස් “තනි පුද්ගලයෙකු විසින් වැඩිපුරම දැවෙන පැරෂුට් පැනීම්” සිදු කර ඇති අතර, ඔහුගේ පැනීම් ගණන 16 වතාවක් වෙනවා.  නව චිත්‍රපටයේ රූගත කිරීම් අතරතුර දකුණු අප්‍රිකාවේ මෙම ක්‍රියාන්විතය සිදු කරන ලද අතර, එය මේ වන විට ප්‍රේක්ෂකයින් මවිතයට පත් කර තිබෙනවා.  ඒ අනුව, ගෝලීය සිනමා ශාලාවල ඩොලර් මිලියන 389ක දැවැන්ත ආදායමක් ද ලබාගෙන ඇති බවටයි විදෙස් මාධ්‍ය වාර්තා කරන්නේ.  රසිකයින්ගේ ප්‍රියතම 'Mission: Impossible' චිත්‍රපට මාලාව 1996 දී ටොම් කෲස් ප්‍රථම වරට රහස් නියෝජිත ඊතන් හන්ට් ලෙස රඟපෑමට එක්වූවා.",
  "timestamp": "2025-06-06T14:35:13",
  "url": "https://hirunews.lk/entertainment/406447/tom-cruise-sets-guinness-world-record-for-mission-impossible",
  "category": "Entertainment"
}