{
  "id": "260ac1ee78146b79e7f2d1f8c9de50b0",
  "source": "News First",
  "headline": "එක්දින පිටියෙන් සමුගන්නේ නෑ- මාධ්‍ය වාර්තාවලට රෝහිත් ශර්මාගෙන් පිළිතුරු..",
  "content": "COLOMBO (News 1st) -තමන් එක්දින ජාත්‍යන්තර ක්‍රිකට් පිටියෙන් විශ්‍රාම නොගන්නා බව ඉන්දීය ක්‍රිකට් නායක රෝහිත් ශර්මා පවසයි.ඔහු මේ බව සඳහන් කළේ , 3වැනි වරටත් ශූරයන්ගේ කුසලාන ක්‍රිකට් තරගාවලිය ජය ගැනීමෙන් අනතුරුව පැවති මාධ්‍ය හමුවේදී ය.රෝහිත් ශර්මා - නායකඉන්දීය ක්‍රිකට් කණ්ඩායම''තවත් දෙයක් මම මේ ආකෘතියෙන් විශ්‍රාම ගන්නෙ නැහැ. මම මේක කියන්නේ ඒ ගැන කටකතා පැතිරෙන එක නවත්තන්න. ඉදිරියට යමු''",
  "timestamp": "2025-03-10 7:53",
  "url": "https://sinhala.newsfirst.lk/2025/03/10/%e0%b6%91%e0%b6%9a%e0%b7%8a%e0%b6%af%e0%b7%92%e0%b6%b1-%e0%b6%b4%e0%b7%92%e0%b6%a7%e0%b7%92%e0%b6%ba%e0%b7%99%e0%b6%b1%e0%b7%8a-%e0%b7%83%e0%b6%b8%e0%b7%94%e0%b6%9c"
}