{
  "id": "aeca433a75e537bd924eacd2ba82f903",
  "source": "hirunews",
  "headline": "අන්තර් පාසල් රග්බි සුපිරි වටයේ තරගවලින් ඉසිපතනයට සහ සාන්ත පීතරයින්ට ජය",
  "content": "ඩයලොග් අන්තර් පාසල් රග්බි පළමු කොටස යටතේ සුපිරි තරග වටයේ පළමු සතිය මේ වන විට ක්‍රියාත්මකයි. ඒ අනුව අද තරග 02 ක් පැවැති අතර එම තරග දෙකෙහි ජය වාර්තා කිරීමට ඉසිපතන විද්‍යාලය සහ බම්බලපිටිය සාන්ත පීතර විද්‍යාලය සමත් වුණා.ඒ අනුව කොළඹ රාජකීය විද්‍යාලය සහ ඉසිපතන විද්‍යාලය අතර පැවති තරගය ගෝල 19 - 18ක් ලෙසත්, බම්බලපිටිය සාන්ත පීතර විද්‍යාලය සහ මහනුවර ත්‍රිත්ව විද්‍යාලය අතර පැවති තරගය ගෝල 37 - 28ක් ලෙසත් ජය වාර්තා කිරීමට සමත් වුණා.",
  "timestamp": "2024-08-10T19:32:40",
  "url": "https://hirunews.lk/sports/378415/අන්තර්-පාසල්-රග්බි-සුපිරි-වටයේ-තරගවලින්-ඉසිපතනයට-සහ-සාන්ත-පීතරයින්ට-ජය",
  "category": "Sports"
}