{
  "id": "7f515277134443f72eb17a8e11bdc273",
  "source": "hirunews",
  "headline": "එංගලන්ත සංචිතය ප්‍රකාශයට",
  "content": "ඉන්දීය කණ්ඩායමට එරෙහි තරග 05කින් සමන්විත ටෙස්ට් ක්‍රිකට් තරගාවලියේ පළමු තරගය සඳහා සහභාගි වන එංගලන්ත සංචිතය ප්‍රකාශයට පත් කර තිබෙනවා.  බෙන් ස්ටෝක්ස්ගේ නායකත්වයෙන් යුත් මෙම සංචිතයට ක්‍රීඩකයින් 14 දෙනෙකු ඇතුළත්.  ෂොයිබ් බෂීර්, ජේකොබ් බෙතෙල්, හැරී බෲක්, බ්‍රයිඩන් කාර්ස්, සෑම් කුක්, සැක් ක්‍රෝලි, බෙන් ඩකට්, ජේමි ඕවර්ටන්, ඔලී පෝප්, ජෝ රූට්, ජෙමි ස්මිත්, ජොෂ් ටොන්ග්, ක්‍රිස් වෝක්ස් මෙම ක්‍රීඩකයින් අතර වනවා.  දෙරට අතර පළමු ටෙස්ට් තරගය මේ මස 20 වනදා ආරම්භ වීමට නියමිතයි.",
  "timestamp": "2025-06-06T07:43:05",
  "url": "https://hirunews.lk/sports/406405/england-squad-announced",
  "category": "Sports"
}