{
  "source": "News First",
  "headline": "එංගලන්තය අවසන් පූර්ව වටයට",
  "content": "COLOMBO (News 1st) &ndash; 2024 පන්දුවාර විස්සයි විස්ස ලෝක කුසලාන ක්&zwj;රිකට් තරගාවලියේ බටහිර ඉන්දීය කොදෙව් කණ්ඩායම සහ දකුණු අප්&zwj;රිකාව අතර තරගය දැන් පැවැත්වෙයි. එහි කාසියේ වාසිය දිනු දකුණු අප්&zwj;රිකා කණ්ඩායම තීරණය කළේ පළමුවෙන් පන්දු රැකීමටයි. මෙම තරගය MTV මාධ්&zwj;ය ජාලයේ TV1 නාලිකාව ඔස්සේ සහ, www.sirasa tv.lk වෙබ් අඩවිය ඔස්සේ ඔබට නැරඹිය හැකියි. මේ අතර, එංගලන්තය පන්දුවාර විස්සයි විස්ස ලෝක කුසලාන ක්&zwj;රිකට් තරගාවලියේ අවසන් පූර්ව වටයේ සිය ස්ථානය තහවුරු කර ගත්තේ ය. ඒ සුපිරි 8 දෙනාගේ වටයේ අමෙරිකාව සමග පැවැති තරගය කඩුළු 10කින් ජය ගනිමින් ය.",
  "timestamp": "2024-06-24 6:59",
  "url": "https://sinhala.newsfirst.lk/2024/06/24/%e0%b6%91%e0%b6%82%e0%b6%9c%e0%b6%bd%e0%b6%b1%e0%b7%8a%e0%b6%ad%e0%b6%ba-%e0%b6%85%e0%b7%80%e0%b7%83%e0%b6%b1%e0%b7%8a-%e0%b6%b4%e0%b7%96%e0%b6%bb%e0%b7%8a%e0%b7%80",
  "category": "sports",
  "category_id": 83,
  "saved_at": "2025-06-24T22:51:20.147742"
}