{
  "id": "dcbef66c351b072d5af0f92f299cb229",
  "source": "hirunews",
  "headline": "පසුගිය මාසයේ සේවා අංශයේ වර්ධනයක්",
  "content": "සංචරණ සීමා ලිහිල් කිරීම හේතුවෙන් පසුගිය මාසයේදී සේවා අංශයේ වර්ධනයක් දක්නට ලැබුණු බව මහ බැංකුව ප්‍රකාශ කළා. ඒ සඳහා වැඩි දායකත්වයක් ලැබී තිබෙන්නේ අපේක්ෂිත ව්‍යාපාර ක්‍රියාකාරකම් ඉහළ යෑමෙන්. කෙසේ වෙතත් තොග සහ සිල්ලර වෙළඳාම, නවාතැන් සහ ආහාර පාන සැපයීම් වැනි උප අංශවල යම් පහළ යාමක්ද වාර්තා වනවා.",
  "timestamp": "2021-07-19T08:33:04",
  "url": "https://hirunews.lk/business/277379/පසුගිය-මාසයේ-සේවා-අංශයේ-වර්ධනයක්",
  "category": "Business"
}