{
  "id": "5218fcce26136660451c5d0ba9e03e82",
  "source": "hirunews",
  "headline": "කැල්ටෙක්ස් වෙතින් පහසුකමක්",
  "content": "මෝටර් රථ ලිහිසි තෙල් අංශය තුළ එක් ලිහිසි තෙල් හුවමාරුවකින් කිලෝමීටර් 10,000 ක් ධාවනය කිරීමේ සුවිශේෂි පහසුකමක් ශ්‍රී ලාංකිකයින්ට හිමි කර දීමට කැල්ටෙක්ස් හැවොලින් කටයුතු කර තිබෙනවා. ඒ එම සමාගම තම ප්‍රෝ ඩී එස් ෆුලී සින්තටික් එකෝ සීරියස් ලිහිසි තෙල් ක්ෂේත්‍රය තුළ අත්හදා බලමින්. තවද පාරිභෝගික අවශ්‍යතා සඳහා විසදුම් සෙවීම වෙනුවෙන් කැල්ටෙක්ස් හැවොලින් හී ආරක්ෂාවද මෙම ක්‍රියාකාරීත්වය තුළින් මනාව සහතික කරනු ලබනවා.ඩිපෝසිට් ෂීල්ඩ් තාක්ෂණය සමග එන කැල්ටෙක්ස් හැවොලින් ප්‍රෝ ඩී එස් ෆුලී සින්තටික් එකෝ එංජින් ලිහිසි තෙල්, එංජින්වල ඉහළ ක්‍රියාකාරීත්වය සඳහා වඩාත් සුදුසු වන අතර අවශ්‍ය සෑම මොහොතකම සුවිශේෂී ආරක්ෂාවක් මෙන්ම කාර්යක්ෂමතාවක් ලබා දෙනවා.එසේම හිටපු ක්‍රිකට් ක්‍රීඩක මහේල ජයවර්ධන කැල්ටෙක්ස් හැව්ලින්හී නිල සන්නාම තානාපතිවරයා ලෙස පත් කිරීමද විශේෂත්වයක්.",
  "timestamp": "2024-01-26T19:51:13",
  "url": "https://hirunews.lk/business/360387/කැල්ටෙක්ස්-වෙතින්-පහසුකමක්",
  "category": "Business"
}