{
  "id": "114e29425011ccd3aa9e7c10139ec61c",
  "source": "Lankadeepa",
  "headline": "ඉරාන විදෙස් ඇමති රුසියාවේ",
  "content": "ඉරාන විදේශ අමාත්‍ය අබ්බාස් අරාග්චි රුසියාව බලා යැෑමට නියමිතය. මේ වනවිට ඉරානයත් රුසියාවත් අතරේ, ඉරාන න්‍යෂ්ටික වැඩසටහන සම්බන්ධයෙන් සාකච්ඡා පැවැත්වෙයි.එම සාකච්ඡා සම්බන්ධයෙන් රුසියාවේ මතය සහ රුසියාවේ අදහස් දැන ගැනීම ඉරාන විදේශ අමාත්‍ය අබ්බාස් අරාග්චිගේ අරමුණ වී ඇතැයි පැවැසෙයි.අරාග්චි රුසියානු විදේශ අමාත්‍ය සර්ජි ලැව්රොව් හමුවී සාකච්ඡා පවත්වනු ඇතැයි ද විදෙස් මාධ්‍ය වාර්තා පෙන්වා දෙයි.(අල් ජසීරා)\n\nඉරාන විදේශ අමාත්‍ය අබ්බාස් අරාග්චි රුසියාව බලා යැෑමට නියමිතය. මේ වනවිට ඉරානයත් රුසියාවත් අතරේ, ඉරාන න්‍යෂ්ටික වැඩසටහන සම්බන්ධයෙන් සාකච්ඡා පැවැත්වෙයි.\n\nඑම සාකච්ඡා සම්බන්ධයෙන් රුසියාවේ මතය සහ රුසියාවේ අදහස් දැන ගැනීම ඉරාන විදේශ අමාත්‍ය අබ්බාස් අරාග්චිගේ අරමුණ වී ඇතැයි පැවැසෙයි.\n\nඅරාග්චි රුසියානු විදේශ අමාත්‍ය සර්ජි ලැව්රොව් හමුවී සාකච්ඡා පවත්වනු ඇතැයි ද විදෙස් මාධ්‍ය වාර්තා පෙන්වා දෙයි.",
  "timestamp": "2025-04-15T00:00:00",
  "url": "https://www.lankadeepa.lk/world_news/ඉරන-වදස-ඇමත-රසයව/14-670258"
}