{
  "source": "News First",
  "headline": "හෙට (12) සිට 15% කින් විදුලි ගාස්තු ඉහළට - මහජන උපයෝගීතා කොමිසම",
  "content": "COLOMBO (News 1st) - විදුලි ගාස්තු හෙට සිට 15% කින් ඉහළ දැමීමට ශ්‍රී ලංකා මහජන උපයෝගිතා කොමිෂන් සභාව යෝජනා කර තිබේ.මහජන උපයෝගිතා කොමිසමේ සභාපති මහාචාර්ය ලලිත් චන්ද්‍රලාල් මහතා මේ බව සඳහන් කළේ ,අද පැවැති මාධ්‍ය හමුවකට එක් වෙමින්.",
  "timestamp": "2025-06-11 1:43",
  "url": "https://sinhala.newsfirst.lk/2025/06/11/%e0%b7%84%e0%b7%99%e0%b6%a7-12-%e0%b7%83%e0%b7%92%e0%b6%a7-15-%e0%b6%9a%e0%b7%92%e0%b6%b1%e0%b7%8a-%e0%b7%80",
  "category": "local",
  "category_id": 81,
  "saved_at": "2025-06-24T22:51:07.815664"
}