{
  "source": "News First",
  "headline": "තේරී පත්වූ පළාත් පාලන සභිකයින්ගේ පළමු කොටස ගැසට් කිරීම අද.",
  "content": "COLOMBO (News1st) - පසුගිය පළාත් පාලන මැතිවරණයෙන් තේරීපත් වූ සහිකයින්ගේ නම් වලින් කොටසක් අද(23) දිනයේ ගැසට් මගින් පළ කරන බව මැතිවරණ කොමිෂන් සභාව පවසයි.මැතිවරණ කොමසාරිස් ජෙනරාල් සමන් ශ්‍රි රත්නායක මහතා සඳහන් කළේ, පළාත් පාලන කොට්ඨාස ජයගත් සියලු සභිකයින්ගේ නම් ඒ අනුව ගැසට් මගින් ප්‍රකාශයට පත් කරන බවයි.ලයිස්තුවලින් තේරීපත්වූ සභිකයින්ගේ නම් මෙතෙක් භාර නොදුන් දේශාපාලන පක්ෂ හා ස්වාධීන කණ්ඩායම් කඩිනමින් එම නම් දිස්ත්‍රික් තේරීම්භාර නිලධාරීන්ට භාර දීමට පියවර ගන්නා ලෙසද මැතිවරණ කොමසාරිස් ජෙනරාල්වරයා දැනුම් දෙයි.",
  "timestamp": "2025-05-23 7:24",
  "url": "https://sinhala.newsfirst.lk/2025/05/23/%e0%b6%ad%e0%b7%9a%e0%b6%bb%e0%b7%93-%e0%b6%b4%e0%b6%ad%e0%b7%8a%e0%b7%80%e0%b7%96-%e0%b6%b4%e0%b7%85%e0%b7%8f%e0%b6%ad%e0%b7%8a-%e0%b6%b4%e0%b7%8f%e0%b6%bd",
  "category": "local",
  "category_id": 81,
  "saved_at": "2025-06-24T22:51:15.100061"
}